routelit_mantine/__init__.py
routelit_mantine/builder.py
routelit_mantine/py.typed
routelit_mantine/utils.py
routelit_mantine/static/frontend.css
routelit_mantine/static/index-C2tvYdiW.js
routelit_mantine/static/index-C2tvYdiW.js.map
routelit_mantine/static/routelit-mantine.es.js
routelit_mantine/static/routelit-mantine.es.js.map
routelit_mantine/static/routelit.svg
routelit_mantine/static/tabler-icons-react-BLcl9MET.js
routelit_mantine/static/tabler-icons-react-BLcl9MET.js.map
routelit_mantine/static/.vite/manifest.json
routelit_mantine-0.1.4.dist-info/METADATA
routelit_mantine-0.1.4.dist-info/WHEEL
routelit_mantine-0.1.4.dist-info/licenses/LICENSE
routelit_mantine-0.1.4.dist-info/RECORD
