Metadata-Version: 2.4
Name: routelit-mantine
Version: 0.1.4
Summary: This is a routelit library repository for that uses uv for their dependency management.
Project-URL: Homepage, https://routelit.github.io/routelit-mantine/
Project-URL: Repository, https://github.com/routelit/routelit-mantine
Project-URL: Documentation, https://routelit.github.io/routelit-mantine/
Author-email: Rolando Gómez Tabar <rolangom@gmail.com>
License-File: LICENSE
Keywords: python
Classifier: Intended Audience :: Developers
Classifier: Programming Language :: Python
Classifier: Programming Language :: Python :: 3
Classifier: Programming Language :: Python :: 3.9
Classifier: Programming Language :: Python :: 3.10
Classifier: Programming Language :: Python :: 3.11
Classifier: Programming Language :: Python :: 3.12
Classifier: Programming Language :: Python :: 3.13
Classifier: Topic :: Software Development :: Libraries :: Python Modules
Requires-Python: <4.0,>=3.9
Requires-Dist: routelit>=0.5.9
